sachima/Color.py
sachima/__init__.py
sachima/alert.py
sachima/api.py
sachima/cache.py
sachima/cli.py
sachima/config.py
sachima/excel_high_light.py
sachima/excelstyle.py
sachima/filter_enum.py
sachima/game.py
sachima/geo.py
sachima/handler.py
sachima/htmlstyle.py
sachima/idcardocr.py
sachima/json_driller.py
sachima/log.py
sachima/mail.py
sachima/main_runner.py
sachima/middleware.py
sachima/model.py
sachima/params.py
sachima/publish.py
sachima/rpc.py
sachima/sachima_http_server.py
sachima/sachima_http_server_flask.py
sachima/sns.py
sachima/start_dev.py
sachima/tools.py
sachima/wrappers.py
sachima/assets/asset-manifest.json
sachima/assets/favicon.ico
sachima/assets/index.html
sachima/assets/manifest.json
sachima/assets/precache-manifest.3630e48b676fb71563d7de176ae822b7.js
sachima/assets/precache-manifest.626175e0cdad597159141754f6a2dd5c.js
sachima/assets/service-worker.js
sachima/assets/static/css/2.8ac118a1.chunk.css
sachima/assets/static/css/main.93fa6cd1.chunk.css
sachima/assets/static/js/2.0cb1a837.chunk.js
sachima/assets/static/js/main.2e2ae152.chunk.js
sachima/assets/static/js/runtime-main.0491173e.js
sachima/example/__init__.py
sachima/example/s_funnel_main.py
sachima/example/s_sankey_main.py
sachima/example/s_scatter3d_main.py
sachima/example/sachima_config.py
sachima/example/example_data/funnel.csv
sachima/example/example_data/life_expectancy.json
sachima/example/example_data/sankey.csv
sachima/example/handler/s_sankey.py
sachima/example/handler/s_scatter3d.py
sachima/example/logs/.keep
sachima/example/services/__init__.py
sachima/example/services/db_connects.py
sachima/views/__init__.py
sachima/views/tohtmlstyle_basic.css
sachima/views/tohtmlstyle_black.css
sachima/views/tohtmlstyle_blue.css
sachima/views/tohtmlstyle_white.css
sachima-2020.8.30.2.dist-info/LICENSE
sachima-2020.8.30.2.dist-info/METADATA
sachima-2020.8.30.2.dist-info/WHEEL
sachima-2020.8.30.2.dist-info/entry_points.txt
sachima-2020.8.30.2.dist-info/top_level.txt
sachima-2020.8.30.2.dist-info/RECORD
