Metadata-Version: 2.1
Name: sachima
Version: 2020.8.30.2
Summary: Better data analysis
Home-page: https://github.com/DessertsLab/Sachima
Author: nocmk2
Author-email: jianye.zhang@gmail.com
License: UNKNOWN
Platform: UNKNOWN
Classifier: Development Status :: 5 - Production/Stable
Classifier: Programming Language :: Python :: 3.5
Classifier: Programming Language :: Python :: 3.6
Classifier: Programming Language :: Python :: 3.7
Classifier: License :: OSI Approved :: MIT License
Classifier: Operating System :: OS Independent
Requires-Dist: aenum
Requires-Dist: click
Requires-Dist: Flask
Requires-Dist: redis
